LICENSE.txt
README.txt
setup.py
src/Products/__init__.py
src/Products.UserAndGroupSelectionWidget.egg-info/PKG-INFO
src/Products.UserAndGroupSelectionWidget.egg-info/SOURCES.txt
src/Products.UserAndGroupSelectionWidget.egg-info/dependency_links.txt
src/Products.UserAndGroupSelectionWidget.egg-info/namespace_packages.txt
src/Products.UserAndGroupSelectionWidget.egg-info/not-zip-safe
src/Products.UserAndGroupSelectionWidget.egg-info/requires.txt
src/Products.UserAndGroupSelectionWidget.egg-info/top_level.txt
src/Products/UserAndGroupSelectionWidget/__init__.py
src/Products/UserAndGroupSelectionWidget/alphabatch.py
src/Products/UserAndGroupSelectionWidget/browser.py
src/Products/UserAndGroupSelectionWidget/configure.zcml
src/Products/UserAndGroupSelectionWidget/interfaces.py
src/Products/UserAndGroupSelectionWidget/memberlookup.py
src/Products/UserAndGroupSelectionWidget/widget.py
src/Products/UserAndGroupSelectionWidget/i18n/manual.pot
src/Products/UserAndGroupSelectionWidget/i18n/rebuildAll.sh
src/Products/UserAndGroupSelectionWidget/i18n/userandgroupselectionwidget-de.po
src/Products/UserAndGroupSelectionWidget/i18n/userandgroupselectionwidget-es.po
src/Products/UserAndGroupSelectionWidget/i18n/userandgroupselectionwidget.pot
src/Products/UserAndGroupSelectionWidget/profile/skins.xml
src/Products/UserAndGroupSelectionWidget/skins/userandgroupselectionwidget/userandgroupselect.js
src/Products/UserAndGroupSelectionWidget/skins/userandgroupselectionwidget/userandgroupselect.js.metadata
src/Products/UserAndGroupSelectionWidget/skins/userandgroupselectionwidget/userandgroupselect.pt
src/Products/UserAndGroupSelectionWidget/skins/userandgroupselectionwidget/userandgroupselect_popup.pt