Metadata-Version: 1.0
Name: Products.UserAndGroupSelectionWidget
Version: 2.0.4
Summary: Archetypes Widget for User and Group Selection, works with many users.
Home-page: https://svn.plone.org/svn/archetypes/MoreFieldsAndWidgets/UserAndGroupSelectionWidget
Author: BlueDynamics Alliance
Author-email: dev@bluedynamics.com
License: BSD
Keywords: zope zope2 plone archetypes widget user
Platform: UNKNOWN
Classifier: Development Status :: 5 - Production/Stable
Classifier: Environment :: Web Environment
Classifier: Framework :: Zope2
Classifier: License :: OSI Approved :: BSD License
Classifier: Operating System :: OS Independent
Classifier: Programming Language :: Python
Classifier: Topic :: Internet :: WWW/HTTP :: Dynamic Content
